[{"question": ["8", "8", "4", "=", "+", "5", "3", "7", " "], "answersLong": "[\"3+4=7\",\"3+5=8\",\"4+3=7\",\"5+3=8\",\"3+84=87\",\"37+8=45\",\"38+7=45\",\"4+83=87\",\"5+78=83\",\"7+38=45\",\"75+8=83\",\"78+5=83\",\"8+37=45\",\"8+75=83\",\"83+4=87\",\"84+3=87\",\"37+48=85\",\"38+47=85\",\"47+38=85\",\"48+37=85\"]", "answersLongCommutative": "[1,3,1,3,5,9,10,6,13,10,14,13,9,14,6,5,17,18,18,17]", "answersShort": "[\"3+4=7\",\"3+5=8\",\"3+84=87\",\"37+8=45\",\"38+7=45\",\"4+83=87\",\"5+78=83\",\"75+8=83\",\"37+48=85\",\"38+47=85\"]", "answersShortCommutative": "[1,3,5,9,10,6,13,14,17,18]", "answersShortCommutations": "[2,2,2,2,2,2,2,2,2,2]", "answersShortRearrangements": "[9999,9999,9999,9999,9999,9999,9999,9999,9999,9999]", "fixed": ["3", "="], "questionCoded": ["8", "8", "4", "~=", "+", "5", "~3", "7", " "], "questionFixed": ["", "", "", "~", "", "", "~", "", ""]}, {"question": ["4", "+", "7", "4", "5", "2", "=", "9", " "], "answersLong": "[\"4=4\",\"4+5=9\",\"5+4=9\",\"2+45=47\",\"2+47=49\",\"42+5=47\",\"42+7=49\",\"45+2=47\",\"47+2=49\",\"5+42=47\",\"7+42=49\",\"25+49=74\",\"29+45=74\",\"45+29=74\",\"45+47=92\",\"47+45=92\",\"49+25=74\"]", "answersLongCommutative": "[9999,1,1,7,11,8,12,7,11,8,12,15,16,16,18,18,15]", "answersShort": "[\"4=4\",\"4+5=9\",\"2+45=47\",\"2+47=49\",\"42+5=47\",\"42+7=49\",\"25+49=74\",\"29+45=74\",\"45+47=92\"]", "answersShortCommutative": "[9999,1,7,11,8,12,15,16,18]", "answersShortCommutations": "[1,2,2,2,2,2,2,2,2]", "answersShortRearrangements": "[9999,9999,9999,9999,9999,9999,9999,9999,9999]", "fixed": ["4", "="], "questionCoded": ["~4", "+", "7", "4", "5", "2", "~=", "9", " "], "questionFixed": ["~", "", "", "", "", "", "~", "", ""]}, {"question": ["6", "=", "9", "5", "+", "6", "4", "1", " "], "answersLong": "[\"1+4=5\",\"1+5=6\",\"4+1=5\",\"4+5=9\",\"5+1=6\",\"5+4=9\",\"5+9=14\",\"6+9=15\",\"9+5=14\",\"9+6=15\",\"1+64=65\",\"4+61=65\",\"4+65=69\",\"5+64=69\",\"61+4=65\",\"64+1=65\",\"64+5=69\",\"65+4=69\",\"16+49=65\",\"19+46=65\",\"46+19=65\",\"49+16=65\"]", "answersLongCommutative": "[5,3,5,1,3,1,9,7,9,7,15,16,11,12,16,15,12,11,19,20,20,19]", "answersShort": "[\"1+4=5\",\"1+5=6\",\"4+5=9\",\"5+9=14\",\"6+9=15\",\"1+64=65\",\"4+61=65\",\"4+65=69\",\"5+64=69\",\"16+49=65\",\"19+46=65\"]", "answersShortCommutative": "[5,3,1,9,7,15,16,11,12,19,20]", "answersShortCommutations": "[2,2,2,2,2,2,2,2,2,2,2]", "answersShortRearrangements": "[9999,9999,9999,9999,9999,9999,9999,9999,9999,9999,9999]", "fixed": ["5", "="], "questionCoded": ["6", "~=", "9", "~5", "+", "6", "4", "1", " "], "questionFixed": ["", "~", "", "~", "", "", "", "", ""]}, {"question": ["7", "3", "6", "4", "1", "+", "6", "=", " "], "answersLong": "[\"1+3=4\",\"1+6=7\",\"3+1=4\",\"3+4=7\",\"4+3=7\",\"6+1=7\",\"6+7=13\",\"7+6=13\",\"1+63=64\",\"3+61=64\",\"3+64=67\",\"4+63=67\",\"61+3=64\",\"63+1=64\",\"63+4=67\",\"64+3=67\",\"16+47=63\",\"17+46=63\",\"46+17=63\",\"47+16=63\"]", "answersLongCommutative": "[5,3,5,1,1,3,7,7,9,10,13,14,10,9,14,13,17,18,18,17]", "answersShort": "[\"1+3=4\",\"1+6=7\",\"3+4=7\",\"6+7=13\",\"1+63=64\",\"3+61=64\",\"3+64=67\",\"4+63=67\",\"16+47=63\",\"17+46=63\"]", "answersShortCommutative": "[5,3,1,7,9,10,13,14,17,18]", "answersShortCommutations": "[2,2,2,2,2,2,2,2,2,2]", "answersShortRearrangements": "[9999,9999,9999,9999,9999,9999,9999,9999,9999,9999]", "fixed": ["+", "="], "questionCoded": ["7", "3", "6", "4", "1", "~+", "6", "~=", " "], "questionFixed": ["", "", "", "", "", "~", "", "~", ""]}, {"question": ["5", "4", "1", "+", "1", "2", "=", "9", " "], "answersLong": "[\"1+4=5\",\"4+1=5\",\"4+5=9\",\"5+4=9\",\"5+9=14\",\"9+5=14\",\"14+5=19\",\"15+4=19\",\"15+9=24\",\"19+5=24\",\"2+49=51\",\"4+15=19\",\"42+9=51\",\"49+2=51\",\"5+14=19\",\"5+19=24\",\"9+15=24\",\"9+42=51\",\"14+15=29\",\"15+14=29\",\"41+51=92\",\"51+41=92\"]", "answersLongCommutative": "[3,3,1,1,6,6,18,19,10,11,12,19,13,12,18,11,10,13,22,22,24,24]", "answersShort": "[\"1+4=5\",\"4+5=9\",\"5+9=14\",\"14+5=19\",\"15+4=19\",\"15+9=24\",\"19+5=24\",\"2+49=51\",\"42+9=51\",\"14+15=29\",\"41+51=92\"]", "answersShortCommutative": "[3,1,6,18,19,10,11,12,13,22,24]", "answersShortCommutations": "[2,2,2,2,2,2,2,2,2,2,2]", "answersShortRearrangements": "[9999,9999,9999,9999,9999,9999,9999,9999,9999,9999,9999]", "fixed": ["5", "="], "questionCoded": ["~5", "4", "1", "+", "1", "2", "~=", "9", " "], "questionFixed": ["~", "", "", "", "", "", "~", "", ""]}, {"question": ["=", "+", "2", "5", "9", "6", "1", "4", " "], "answersLong": "[\"1+4=5\",\"2+4=6\",\"4+1=5\",\"4+2=6\",\"4+5=9\",\"5+4=9\",\"5+9=14\",\"9+5=14\",\"15+9=24\",\"19+5=24\",\"2+49=51\",\"42+9=51\",\"49+2=51\",\"5+19=24\",\"9+15=24\",\"9+42=51\",\"16+29=45\",\"19+26=45\",\"26+19=45\",\"29+16=45\"]", "answersLongCommutative": "[4,6,4,6,0,0,10,10,20,21,22,23,22,21,20,23,28,29,29,28]", "answersShort": "[\"1+4=5\",\"2+4=6\",\"4+5=9\",\"5+9=14\",\"15+9=24\",\"19+5=24\",\"2+49=51\",\"42+9=51\",\"16+29=45\",\"19+26=45\"]", "answersShortCommutative": "[4,6,0,10,20,21,22,23,28,29]", "answersShortCommutations": "[2,2,2,2,2,2,2,2,2,2]", "answersShortRearrangements": "[9999,9999,9999,9999,9999,9999,9999,9999,9999,9999]", "fixed": ["4", "="], "questionCoded": ["~=", "+", "2", "5", "9", "6", "1", "~4", " "], "questionFixed": ["~", "", "", "", "", "", "", "~", ""]}, {"question": ["5", "/", "8", "=", "7", "-", "4", "3", " "], "answersLong": "[\"7-3=4\",\"7-4=3\",\"8-3=5\",\"8-5=3\",\"45-37=8\",\"45-38=7\",\"45-7=38\",\"45-8=37\",\"5-8\\/4=3\",\"45\\/3-7=8\",\"45\\/3-8=7\"]", "answersLongCommutative": "[9999,9999,9999,9999,9999,9999,9999,9999,9999,9999,9999]", "answersShort": "[\"7-3=4\",\"7-4=3\",\"8-3=5\",\"8-5=3\",\"45-37=8\",\"45-38=7\",\"45-7=38\",\"45-8=37\",\"5-8\\/4=3\",\"45\\/3-7=8\",\"45\\/3-8=7\"]", "answersShortCommutative": "[9999,9999,9999,9999,9999,9999,9999,9999,9999,9999,9999]", "answersShortCommutations": "[1,1,1,1,1,1,1,1,1,1,1]", "answersShortRearrangements": "[0,0,2,2,4,5,5,4,9999,10,10]", "fixed": ["3", "="], "questionCoded": ["5", "/", "8", "~=", "7", "-", "4", "~3", " "], "questionFixed": ["", "", "", "~", "", "", "", "~", ""]}, {"question": ["2", "9", "2", "4", "=", "/", "-", "3", " "], "answersLong": "[\"2=2\",\"4-2=2\",\"4\\/2=2\",\"4-2\\/2=3\",\"92\\/23=4\",\"92\\/4=23\",\"24\\/2-3=9\",\"24\\/2-9=3\"]", "answersLongCommutative": "[9999,9999,9999,9999,9999,9999,9999,9999]", "answersShort": "[\"2=2\",\"4-2=2\",\"4\\/2=2\",\"4-2\\/2=3\",\"92\\/23=4\",\"92\\/4=23\",\"24\\/2-3=9\",\"24\\/2-9=3\"]", "answersShortCommutative": "[9999,9999,9999,9999,9999,9999,9999,9999]", "answersShortCommutations": "[1,1,1,1,1,1,1,1]", "answersShortRearrangements": "[9999,9999,9999,9999,4,4,6,6]", "fixed": ["2", "="], "questionCoded": ["~2", "9", "2", "4", "~=", "/", "-", "3", " "], "questionFixed": ["~", "", "", "", "~", "", "", "", ""]}, {"question": ["1", "3", "+", "8", "7", "=", "5", "1", " "], "answersLong": "[\"1+7=8\",\"3+5=8\",\"5+3=8\",\"7+1=8\",\"3+8=11\",\"5+8=13\",\"7+8=15\",\"8+3=11\",\"8+5=13\",\"8+7=15\",\"13+5=18\",\"15+3=18\",\"3+15=18\",\"5+13=18\",\"13+58=71\",\"17+18=35\",\"18+17=35\",\"18+53=71\",\"53+18=71\",\"58+13=71\"]", "answersLongCommutative": "[1,3,3,1,5,9,7,5,9,7,11,12,12,11,15,16,16,18,18,15]", "answersShort": "[\"1+7=8\",\"3+5=8\",\"3+8=11\",\"5+8=13\",\"7+8=15\",\"13+5=18\",\"15+3=18\",\"13+58=71\",\"17+18=35\",\"18+53=71\"]", "answersShortCommutative": "[1,3,5,9,7,11,12,15,16,18]", "answersShortCommutations": "[2,2,2,2,2,2,2,2,2,2]", "answersShortRearrangements": "[9999,9999,9999,9999,9999,9999,9999,9999,9999,9999]", "fixed": ["8", "="], "questionCoded": ["1", "3", "+", "~8", "7", "~=", "5", "1", " "], "questionFixed": ["", "", "", "~", "", "~", "", "", ""]}, {"question": ["=", "4", "1", "4", "7", "8", "+", "3", " "], "answersLong": "[\"1+3=4\",\"1+7=8\",\"3+1=4\",\"7+1=8\",\"1+47=48\",\"34+7=41\",\"37+4=41\",\"4+37=41\",\"41+7=48\",\"47+1=48\",\"7+34=41\",\"7+41=48\",\"34+47=81\",\"37+44=81\",\"44+37=81\",\"47+34=81\"]", "answersLongCommutative": "[6,3,6,3,8,12,13,13,9,8,12,9,16,17,17,16]", "answersShort": "[\"1+3=4\",\"1+7=8\",\"1+47=48\",\"34+7=41\",\"37+4=41\",\"41+7=48\",\"34+47=81\",\"37+44=81\"]", "answersShortCommutative": "[6,3,8,12,13,9,16,17]", "answersShortCommutations": "[2,2,2,2,2,2,2,2]", "answersShortRearrangements": "[9999,9999,9999,9999,9999,9999,9999,9999]", "fixed": ["1", "="], "questionCoded": ["~=", "4", "~1", "4", "7", "8", "+", "3", " "], "questionFixed": ["~", "", "~", "", "", "", "", "", ""]}]